outformer/__init__.py
outformer/core/__init__.py
outformer/core/jsonformer.py
outformer/core/token_processors.py
outformer/formatters/__init__.py
outformer/formatters/highlight.py
outformer-0.1.3.dist-info/LICENSE
outformer-0.1.3.dist-info/METADATA
outformer-0.1.3.dist-info/WHEEL
outformer-0.1.3.dist-info/RECORD
