Metadata-Version: 2.3
Name: outformer
Version: 0.1.3
Summary: Structure Outputs from Language Models
License: MIT
Keywords: JSON,structured output,LLM,Structure,Transformers,NLP
Author: milistu
Author-email: studen.m98@gmail.com
Requires-Python: <=3.12, >=3.10
Classifier: Intended Audience :: Science/Research
Classifier: License :: OSI Approved :: Apache Software License
Classifier: Programming Language :: Python :: 3.10
Classifier: Programming Language :: Python :: 3.11
Classifier: Programming Language :: Python :: 3.12
Classifier: Topic :: Scientific/Engineering :: Artificial Intelligence
Requires-Dist: termcolor (>=3.1.0,<4.0.0)
Requires-Dist: torch (>=2.7.0,<3.0.0)
Requires-Dist: transformers (>=4.51.3,<5.0.0)
